{
  "elapsed_secs": 680.0193591117859,
  "spent_eps_deltas": [
    [
      0.5013214470892815,
      0.005120140500366688
    ]
  ],
  "train_accuracy": 0.6197,
  "test_accuracy": 0.6237,
  "num_training_steps": 600,
  "mistakes": null,
  "result_series": [
    {
      "step": 10,
      "elapsed_secs": 14.75496220588684,
      "spent_eps_deltas": [
        [
          0.5000220234312129,
          0.005002002231776714
        ]
      ],
      "train_accuracy": 0.1815,
      "test_accuracy": 0.1797,
      "mistakes": null
    },
    {
      "step": 20,
      "elapsed_secs": 11.942791938781738,
      "spent_eps_deltas": [
        [
          0.5000440756921448,
          0.005004004575312138
        ]
      ],
      "train_accuracy": 0.2842,
      "test_accuracy": 0.2883,
      "mistakes": null
    },
    {
      "step": 30,
      "elapsed_secs": 11.672610998153687,
      "spent_eps_deltas": [
        [
          0.5000661269806007,
          0.005006006918847561
        ]
      ],
      "train_accuracy": 0.3738,
      "test_accuracy": 0.3809,
      "mistakes": null
    },
    {
      "step": 40,
      "elapsed_secs": 13.111095905303955,
      "spent_eps_deltas": [
        [
          0.5000881772967095,
          0.005008009262382984
        ]
      ],
      "train_accuracy": 0.3913,
      "test_accuracy": 0.4001,
      "mistakes": null
    },
    {
      "step": 50,
      "elapsed_secs": 11.458451271057129,
      "spent_eps_deltas": [
        [
          0.5001102266405998,
          0.0050100116059184074
        ]
      ],
      "train_accuracy": 0.4474,
      "test_accuracy": 0.4554,
      "mistakes": null
    },
    {
      "step": 60,
      "elapsed_secs": 11.542794942855835,
      "spent_eps_deltas": [
        [
          0.5001322750124001,
          0.005012013949453831
        ]
      ],
      "train_accuracy": 0.5049,
      "test_accuracy": 0.5133,
      "mistakes": null
    },
    {
      "step": 70,
      "elapsed_secs": 11.035211086273193,
      "spent_eps_deltas": [
        [
          0.500154322412239,
          0.005014016292989254
        ]
      ],
      "train_accuracy": 0.5081,
      "test_accuracy": 0.5166,
      "mistakes": null
    },
    {
      "step": 80,
      "elapsed_secs": 11.3470778465271,
      "spent_eps_deltas": [
        [
          0.500176368840245,
          0.005016018636524677
        ]
      ],
      "train_accuracy": 0.5084,
      "test_accuracy": 0.5162,
      "mistakes": null
    },
    {
      "step": 90,
      "elapsed_secs": 11.002272844314575,
      "spent_eps_deltas": [
        [
          0.5001984142965465,
          0.0050180209800601006
        ]
      ],
      "train_accuracy": 0.4915,
      "test_accuracy": 0.4926,
      "mistakes": null
    },
    {
      "step": 100,
      "elapsed_secs": 11.2678542137146,
      "spent_eps_deltas": [
        [
          0.5002204587812723,
          0.005020023323595524
        ]
      ],
      "train_accuracy": 0.5633,
      "test_accuracy": 0.5752,
      "mistakes": null
    },
    {
      "step": 110,
      "elapsed_secs": 11.050118923187256,
      "spent_eps_deltas": [
        [
          0.5002425022945506,
          0.005022025667130947
        ]
      ],
      "train_accuracy": 0.5714,
      "test_accuracy": 0.5759,
      "mistakes": null
    },
    {
      "step": 120,
      "elapsed_secs": 11.251235961914062,
      "spent_eps_deltas": [
        [
          0.5002645448365098,
          0.00502402801066637
        ]
      ],
      "train_accuracy": 0.5698,
      "test_accuracy": 0.5847,
      "mistakes": null
    },
    {
      "step": 130,
      "elapsed_secs": 11.344836950302124,
      "spent_eps_deltas": [
        [
          0.5002865864072784,
          0.005026030354201794
        ]
      ],
      "train_accuracy": 0.5722,
      "test_accuracy": 0.5743,
      "mistakes": null
    },
    {
      "step": 140,
      "elapsed_secs": 11.207700967788696,
      "spent_eps_deltas": [
        [
          0.5003086270069846,
          0.005028032697737217
        ]
      ],
      "train_accuracy": 0.5673,
      "test_accuracy": 0.5797,
      "mistakes": null
    },
    {
      "step": 150,
      "elapsed_secs": 10.9448561668396,
      "spent_eps_deltas": [
        [
          0.500330666635757,
          0.00503003504127264
        ]
      ],
      "train_accuracy": 0.5695,
      "test_accuracy": 0.581,
      "mistakes": null
    },
    {
      "step": 160,
      "elapsed_secs": 11.168904781341553,
      "spent_eps_deltas": [
        [
          0.5003527052937237,
          0.0050320373848080635
        ]
      ],
      "train_accuracy": 0.607,
      "test_accuracy": 0.6043,
      "mistakes": null
    },
    {
      "step": 170,
      "elapsed_secs": 11.27831506729126,
      "spent_eps_deltas": [
        [
          0.500374742981013,
          0.005034039728343487
        ]
      ],
      "train_accuracy": 0.5984,
      "test_accuracy": 0.5968,
      "mistakes": null
    },
    {
      "step": 180,
      "elapsed_secs": 11.172247171401978,
      "spent_eps_deltas": [
        [
          0.5003967796977532,
          0.00503604207187891
        ]
      ],
      "train_accuracy": 0.6068,
      "test_accuracy": 0.6026,
      "mistakes": null
    },
    {
      "step": 190,
      "elapsed_secs": 11.2882719039917,
      "spent_eps_deltas": [
        [
          0.5004188154440724,
          0.005038044415414333
        ]
      ],
      "train_accuracy": 0.6181,
      "test_accuracy": 0.6168,
      "mistakes": null
    },
    {
      "step": 200,
      "elapsed_secs": 11.330355167388916,
      "spent_eps_deltas": [
        [
          0.500440850220099,
          0.005040046758949757
        ]
      ],
      "train_accuracy": 0.6021,
      "test_accuracy": 0.604,
      "mistakes": null
    },
    {
      "step": 210,
      "elapsed_secs": 11.146522760391235,
      "spent_eps_deltas": [
        [
          0.500462884025961,
          0.00504204910248518
        ]
      ],
      "train_accuracy": 0.6047,
      "test_accuracy": 0.6052,
      "mistakes": null
    },
    {
      "step": 220,
      "elapsed_secs": 11.117321014404297,
      "spent_eps_deltas": [
        [
          0.5004849168617864,
          0.005044051446020603
        ]
      ],
      "train_accuracy": 0.6336,
      "test_accuracy": 0.6286,
      "mistakes": null
    },
    {
      "step": 230,
      "elapsed_secs": 11.132446050643921,
      "spent_eps_deltas": [
        [
          0.5005069487277036,
          0.0050460537895560265
        ]
      ],
      "train_accuracy": 0.6333,
      "test_accuracy": 0.6345,
      "mistakes": null
    },
    {
      "step": 240,
      "elapsed_secs": 11.147486925125122,
      "spent_eps_deltas": [
        [
          0.5005289796238407,
          0.00504805613309145
        ]
      ],
      "train_accuracy": 0.6544,
      "test_accuracy": 0.651,
      "mistakes": null
    },
    {
      "step": 250,
      "elapsed_secs": 11.01324725151062,
      "spent_eps_deltas": [
        [
          0.5005510095503254,
          0.005050058476626873
        ]
      ],
      "train_accuracy": 0.6163,
      "test_accuracy": 0.6175,
      "mistakes": null
    },
    {
      "step": 260,
      "elapsed_secs": 11.128394842147827,
      "spent_eps_deltas": [
        [
          0.5005730385072861,
          0.005052060820162296
        ]
      ],
      "train_accuracy": 0.6293,
      "test_accuracy": 0.6321,
      "mistakes": null
    },
    {
      "step": 270,
      "elapsed_secs": 11.257900953292847,
      "spent_eps_deltas": [
        [
          0.5005950664948504,
          0.00505406316369772
        ]
      ],
      "train_accuracy": 0.6383,
      "test_accuracy": 0.6508,
      "mistakes": null
    },
    {
      "step": 280,
      "elapsed_secs": 10.885498046875,
      "spent_eps_deltas": [
        [
          0.5006170935131466,
          0.005056065507233143
        ]
      ],
      "train_accuracy": 0.6097,
      "test_accuracy": 0.6323,
      "mistakes": null
    },
    {
      "step": 290,
      "elapsed_secs": 11.027765035629272,
      "spent_eps_deltas": [
        [
          0.5006391195623027,
          0.005058067850768566
        ]
      ],
      "train_accuracy": 0.6184,
      "test_accuracy": 0.6288,
      "mistakes": null
    },
    {
      "step": 300,
      "elapsed_secs": 11.149093866348267,
      "spent_eps_deltas": [
        [
          0.5006611446424463,
          0.005060070194303989
        ]
      ],
      "train_accuracy": 0.6114,
      "test_accuracy": 0.624,
      "mistakes": null
    },
    {
      "step": 310,
      "elapsed_secs": 11.07712197303772,
      "spent_eps_deltas": [
        [
          0.5006831687537053,
          0.005062072537839413
        ]
      ],
      "train_accuracy": 0.6072,
      "test_accuracy": 0.6165,
      "mistakes": null
    },
    {
      "step": 320,
      "elapsed_secs": 11.083483934402466,
      "spent_eps_deltas": [
        [
          0.5007051918962078,
          0.005064074881374836
        ]
      ],
      "train_accuracy": 0.605,
      "test_accuracy": 0.6157,
      "mistakes": null
    },
    {
      "step": 330,
      "elapsed_secs": 11.214495182037354,
      "spent_eps_deltas": [
        [
          0.5007272140700814,
          0.005066077224910259
        ]
      ],
      "train_accuracy": 0.6205,
      "test_accuracy": 0.6197,
      "mistakes": null
    },
    {
      "step": 340,
      "elapsed_secs": 11.138071775436401,
      "spent_eps_deltas": [
        [
          0.500749235275454,
          0.0050680795684456825
        ]
      ],
      "train_accuracy": 0.6243,
      "test_accuracy": 0.622,
      "mistakes": null
    },
    {
      "step": 350,
      "elapsed_secs": 10.975872039794922,
      "spent_eps_deltas": [
        [
          0.5007712555124534,
          0.005070081911981106
        ]
      ],
      "train_accuracy": 0.623,
      "test_accuracy": 0.6196,
      "mistakes": null
    },
    {
      "step": 360,
      "elapsed_secs": 10.855854034423828,
      "spent_eps_deltas": [
        [
          0.5007932747812073,
          0.005072084255516529
        ]
      ],
      "train_accuracy": 0.6184,
      "test_accuracy": 0.6191,
      "mistakes": null
    },
    {
      "step": 370,
      "elapsed_secs": 11.154994010925293,
      "spent_eps_deltas": [
        [
          0.5008152930818434,
          0.005074086599051952
        ]
      ],
      "train_accuracy": 0.6406,
      "test_accuracy": 0.6362,
      "mistakes": null
    },
    {
      "step": 380,
      "elapsed_secs": 11.133743047714233,
      "spent_eps_deltas": [
        [
          0.5008373104144894,
          0.005076088942587376
        ]
      ],
      "train_accuracy": 0.6477,
      "test_accuracy": 0.6484,
      "mistakes": null
    },
    {
      "step": 390,
      "elapsed_secs": 11.120764970779419,
      "spent_eps_deltas": [
        [
          0.5008593267792729,
          0.005078091286122799
        ]
      ],
      "train_accuracy": 0.6594,
      "test_accuracy": 0.6516,
      "mistakes": null
    },
    {
      "step": 400,
      "elapsed_secs": 11.108558177947998,
      "spent_eps_deltas": [
        [
          0.5008813421763216,
          0.005080093629658222
        ]
      ],
      "train_accuracy": 0.649,
      "test_accuracy": 0.641,
      "mistakes": null
    },
    {
      "step": 410,
      "elapsed_secs": 11.102916717529297,
      "spent_eps_deltas": [
        [
          0.5009033566057631,
          0.0050820959731936455
        ]
      ],
      "train_accuracy": 0.6495,
      "test_accuracy": 0.6449,
      "mistakes": null
    },
    {
      "step": 420,
      "elapsed_secs": 12.079822063446045,
      "spent_eps_deltas": [
        [
          0.500925370067725,
          0.005084098316729069
        ]
      ],
      "train_accuracy": 0.6405,
      "test_accuracy": 0.6338,
      "mistakes": null
    },
    {
      "step": 430,
      "elapsed_secs": 12.24670124053955,
      "spent_eps_deltas": [
        [
          0.5009473825623346,
          0.005086100660264492
        ]
      ],
      "train_accuracy": 0.6412,
      "test_accuracy": 0.6318,
      "mistakes": null
    },
    {
      "step": 440,
      "elapsed_secs": 11.766791820526123,
      "spent_eps_deltas": [
        [
          0.5009693940897197,
          0.005088103003799915
        ]
      ],
      "train_accuracy": 0.6084,
      "test_accuracy": 0.6058,
      "mistakes": null
    },
    {
      "step": 450,
      "elapsed_secs": 10.80825400352478,
      "spent_eps_deltas": [
        [
          0.5009914046500078,
          0.005090105347335339
        ]
      ],
      "train_accuracy": 0.5767,
      "test_accuracy": 0.5718,
      "mistakes": null
    },
    {
      "step": 460,
      "elapsed_secs": 12.234686851501465,
      "spent_eps_deltas": [
        [
          0.5010134142433262,
          0.005092107690870762
        ]
      ],
      "train_accuracy": 0.6078,
      "test_accuracy": 0.599,
      "mistakes": null
    },
    {
      "step": 470,
      "elapsed_secs": 11.101085186004639,
      "spent_eps_deltas": [
        [
          0.5010354228698023,
          0.005094110034406185
        ]
      ],
      "train_accuracy": 0.5971,
      "test_accuracy": 0.5788,
      "mistakes": null
    },
    {
      "step": 480,
      "elapsed_secs": 11.216819047927856,
      "spent_eps_deltas": [
        [
          0.5010574305295636,
          0.005096112377941608
        ]
      ],
      "train_accuracy": 0.5907,
      "test_accuracy": 0.5755,
      "mistakes": null
    },
    {
      "step": 490,
      "elapsed_secs": 11.255521059036255,
      "spent_eps_deltas": [
        [
          0.5010794372227376,
          0.005098114721477032
        ]
      ],
      "train_accuracy": 0.5756,
      "test_accuracy": 0.5729,
      "mistakes": null
    },
    {
      "step": 500,
      "elapsed_secs": 11.18320107460022,
      "spent_eps_deltas": [
        [
          0.5011014429494515,
          0.005100117065012455
        ]
      ],
      "train_accuracy": 0.5768,
      "test_accuracy": 0.5825,
      "mistakes": null
    },
    {
      "step": 510,
      "elapsed_secs": 11.273174047470093,
      "spent_eps_deltas": [
        [
          0.5011234477098325,
          0.005102119408547878
        ]
      ],
      "train_accuracy": 0.5937,
      "test_accuracy": 0.5906,
      "mistakes": null
    },
    {
      "step": 520,
      "elapsed_secs": 11.267173767089844,
      "spent_eps_deltas": [
        [
          0.5011454515040081,
          0.0051041217520833015
        ]
      ],
      "train_accuracy": 0.6197,
      "test_accuracy": 0.6277,
      "mistakes": null
    },
    {
      "step": 530,
      "elapsed_secs": 11.234827041625977,
      "spent_eps_deltas": [
        [
          0.5011674543321055,
          0.005106124095618725
        ]
      ],
      "train_accuracy": 0.6378,
      "test_accuracy": 0.6483,
      "mistakes": null
    },
    {
      "step": 540,
      "elapsed_secs": 11.275758981704712,
      "spent_eps_deltas": [
        [
          0.5011894561942519,
          0.005108126439154148
        ]
      ],
      "train_accuracy": 0.6121,
      "test_accuracy": 0.62,
      "mistakes": null
    },
    {
      "step": 550,
      "elapsed_secs": 11.275196075439453,
      "spent_eps_deltas": [
        [
          0.5012114570905745,
          0.005110128782689571
        ]
      ],
      "train_accuracy": 0.628,
      "test_accuracy": 0.6344,
      "mistakes": null
    },
    {
      "step": 560,
      "elapsed_secs": 11.223628997802734,
      "spent_eps_deltas": [
        [
          0.5012334570212006,
          0.005112131126224995
        ]
      ],
      "train_accuracy": 0.621,
      "test_accuracy": 0.6155,
      "mistakes": null
    },
    {
      "step": 570,
      "elapsed_secs": 11.008196830749512,
      "spent_eps_deltas": [
        [
          0.5012554559862572,
          0.005114133469760418
        ]
      ],
      "train_accuracy": 0.6358,
      "test_accuracy": 0.6331,
      "mistakes": null
    },
    {
      "step": 580,
      "elapsed_secs": 11.192572116851807,
      "spent_eps_deltas": [
        [
          0.5012774539858714,
          0.005116135813295841
        ]
      ],
      "train_accuracy": 0.6197,
      "test_accuracy": 0.6271,
      "mistakes": null
    },
    {
      "step": 590,
      "elapsed_secs": 10.983932971954346,
      "spent_eps_deltas": [
        [
          0.5012994510201706,
          0.0051181381568312645
        ]
      ],
      "train_accuracy": 0.622,
      "test_accuracy": 0.6275,
      "mistakes": null
    },
    {
      "step": 600,
      "elapsed_secs": 11.248497009277344,
      "spent_eps_deltas": [
        [
          0.5013214470892815,
          0.005120140500366688
        ]
      ],
      "train_accuracy": 0.6197,
      "test_accuracy": 0.6237,
      "mistakes": null
    }
  ],
  "accountant_type": "Amortized",
  "task_id": 0,
  "batch_size": 600,
  "projection_dimensions": 60,
  "default_gradient_l2norm_bound": 4.0,
  "num_hidden_layers": 1,
  "hidden_layer_num_units": 1000,
  "num_examples": 60000,
  "learning_rate": 0.05,
  "end_learning_rate": 0.05,
  "learning_rate_saturate_epochs": 0.0,
  "flag_eps": 0.1,
  "flag_delta": 1e-05,
  "flag_pca_eps": 0.5,
  "flag_pca_delta": 0.005
}
